<annotation>
	<folder>train</folder>
	<filename>143.jpg</filename>
	<path>C:\Users\Macky\Desktop\object_detection_demo-master\object_detection_demo-master\data\images\train\143.jpg</path>
	<source>
		<database>Unknown</database>
	</source>
	<size>
		<width>800</width>
		<height>600</height>
		<depth>3</depth>
	</size>
	<segmented>0</segmented>
	<object>
		<name>Cacaopod</name>
		<pose>Unspecified</pose>
		<truncated>0</truncated>
		<difficult>0</difficult>
		<bndbox>
			<xmin>268</xmin>
			<ymin>142</ymin>
			<xmax>544</xmax>
			<ymax>307</ymax>
		</bndbox>
	</object>
	<object>
		<name>Cacaopod</name>
		<pose>Unspecified</pose>
		<truncated>0</truncated>
		<difficult>0</difficult>
		<bndbox>
			<xmin>341</xmin>
			<ymin>336</ymin>
			<xmax>547</xmax>
			<ymax>535</ymax>
		</bndbox>
	</object>
	<object>
		<name>Cacaopod</name>
		<pose>Unspecified</pose>
		<truncated>0</truncated>
		<difficult>0</difficult>
		<bndbox>
			<xmin>81</xmin>
			<ymin>319</ymin>
			<xmax>245</xmax>
			<ymax>453</ymax>
		</bndbox>
	</object>
	<object>
		<name>Cacaopod</name>
		<pose>Unspecified</pose>
		<truncated>0</truncated>
		<difficult>0</difficult>
		<bndbox>
			<xmin>23</xmin>
			<ymin>223</ymin>
			<xmax>157</xmax>
			<ymax>352</ymax>
		</bndbox>
	</object>
</annotation>
